piston_rspy-0.4.3.dist-info/METADATA
piston_rspy-0.4.3.dist-info/WHEEL
piston_rspy-0.4.3.dist-info/license_files/LICENSE
piston_rspy/piston_rspy.pyi
piston_rspy/py.typed
piston_rspy/__init__.py
piston_rspy/piston_rspy.cp310-win32.pyd
piston_rspy-0.4.3.dist-info/RECORD
