Metadata-Version: 2.1
Name: piston_rspy
Version: 0.4.3
Classifier: Development Status :: 4 - Beta
Classifier: Framework :: AsyncIO
Classifier: License :: OSI Approved :: MIT License
Classifier: Operating System :: OS Independent
Classifier: Programming Language :: Rust
Classifier: Programming Language :: Python :: 3 :: Only
Classifier: Programming Language :: Python :: 3.8
Classifier: Programming Language :: Python :: 3.9
Classifier: Programming Language :: Python :: 3.10
Classifier: Programming Language :: Python :: 3.11
Classifier: Programming Language :: Python :: 3.12
Classifier: Programming Language :: Python :: Implementation :: CPython
Classifier: Topic :: Software Development :: Libraries :: Python Modules
Classifier: Typing :: Typed
License-File: LICENSE
Summary: Python bindings for piston_rs.
Keywords: piston-rs,piston,emkc,code
Home-Page: https://github.com/Jonxslays/piston_rspy
Author: Jonxslays
License: MIT
Requires-Python: >=3.8, <3.13
Project-URL: homepage, https://github.com/Jonxslays/piston_rspy
Project-URL: repository, https://github.com/Jonxslays/piston_rspy
Project-URL: documentation, https://jonxslays.github.io/piston_rspy/piston_rspy/
